django_templatetag_sugarv2-1.0.1.dist-info/top_level.txt
django_templatetag_sugarv2-1.0.1.dist-info/WHEEL
django_templatetag_sugarv2-1.0.1.dist-info/RECORD
django_templatetag_sugarv2-1.0.1.dist-info/METADATA
django_templatetag_sugarv2-1.0.1.dist-info/metadata.json
django_templatetag_sugarv2-1.0.1.dist-info/DESCRIPTION.rst
templatetag_sugar/models.py
templatetag_sugar/node.py
templatetag_sugar/register.py
templatetag_sugar/parser.py
templatetag_sugar/__init__.py
